regressiontestingpackagewithanamethatnooneelsewilluse/__init__.py
regressiontestingpackagewithanamethatnooneelsewilluse/daily_report.py
regressiontestingpackagewithanamethatnooneelsewilluse/log_parameter.py
regressiontestingpackagewithanamethatnooneelsewilluse/report_generation.py
regressiontestingpackagewithanamethatnooneelsewilluse-0.0.2.dist-info/METADATA
regressiontestingpackagewithanamethatnooneelsewilluse-0.0.2.dist-info/WHEEL
regressiontestingpackagewithanamethatnooneelsewilluse-0.0.2.dist-info/RECORD
