Metadata-Version: 2.1
Name: regressiontestingpackagewithanamethatnooneelsewilluse
Version: 0.0.2
Summary: Regression testing package
Project-URL: Homepage, https://github.com/Emerge-Lab/regression-testing
Author-email: Alex Tang <at5604@nyu.edu>
Classifier: License :: OSI Approved :: MIT License
Classifier: Operating System :: OS Independent
Classifier: Programming Language :: Python :: 3
Requires-Python: >=3.8
